api_gateway_dynamodb/__init__.py
api_gateway_dynamodb/api_gateway_dynamodb.py
api_gateway_dynamodb-0.1.2.dist-info/METADATA
api_gateway_dynamodb-0.1.2.dist-info/WHEEL
api_gateway_dynamodb-0.1.2.dist-info/top_level.txt
api_gateway_dynamodb-0.1.2.dist-info/RECORD
