Metadata-Version: 2.2
Name: api_gateway_dynamodb
Version: 0.1.2
Summary: Library for interacting with API Gateway and DynamoDB
Home-page: https://github.com/MsiziGCBG/aws-data-connections-via-api-gateway
Author: Msizi Gumede
Author-email: msizi@cyberneticbg.com
Classifier: Programming Language :: Python :: 3
Classifier: License :: OSI Approved :: MIT License
Classifier: Operating System :: OS Independent
Requires-Python: >=3.8
Requires-Dist: requests
Dynamic: author
Dynamic: author-email
Dynamic: classifier
Dynamic: description
Dynamic: description-content-type
Dynamic: home-page
Dynamic: requires-dist
Dynamic: requires-python
Dynamic: summary
